nebius/__init__.py
nebius/sdk.py
nebius/aio/__init__.py
nebius/aio/abc.py
nebius/aio/base.py
nebius/aio/channel.py
nebius/aio/cli_config.py
nebius/aio/client.py
nebius/aio/constant_channel.py
nebius/aio/idempotency.py
nebius/aio/operation.py
nebius/aio/request.py
nebius/aio/request_kwargs.py
nebius/aio/request_status.py
nebius/aio/service_descriptor.py
nebius/aio/service_error.py
nebius/aio/authorization/__init__.py
nebius/aio/authorization/authorization.py
nebius/aio/authorization/options.py
nebius/aio/authorization/token.py
nebius/aio/token/__init__.py
nebius/aio/token/deferred_channel.py
nebius/aio/token/exchangeable.py
nebius/aio/token/federated_credentials.py
nebius/aio/token/federation_account.py
nebius/aio/token/file.py
nebius/aio/token/options.py
nebius/aio/token/renewable.py
nebius/aio/token/service_account.py
nebius/aio/token/static.py
nebius/aio/token/token.py
nebius/aio/token/federation_bearer/__init__.py
nebius/aio/token/federation_bearer/auth.py
nebius/aio/token/federation_bearer/constants.py
nebius/aio/token/federation_bearer/is_wsl.py
nebius/aio/token/federation_bearer/pkce.py
nebius/aio/token/federation_bearer/server.py
nebius/aio/token/file_cache/__init__.py
nebius/aio/token/file_cache/async_flock.py
nebius/aio/token/file_cache/async_renewable_bearer.py
nebius/aio/token/file_cache/file_bearer.py
nebius/aio/token/file_cache/renewable_bearer.py
nebius/aio/token/file_cache/throttled_token_cache.py
nebius/aio/token/file_cache/token_cache.py
nebius/api/__init__.py
nebius/api/buf/__init__.py
nebius/api/buf/validate/__init__.py
nebius/api/buf/validate/validate_pb2.py
nebius/api/buf/validate/validate_pb2.pyi
nebius/api/buf/validate/validate_pb2_grpc.py
nebius/api/nebius/__init__.py
nebius/api/nebius/annotations_pb2.py
nebius/api/nebius/annotations_pb2.pyi
nebius/api/nebius/annotations_pb2_grpc.py
nebius/api/nebius/applications/__init__.py
nebius/api/nebius/applications/v1alpha1/__init__.py
nebius/api/nebius/applications/v1alpha1/k8s_release_pb2.py
nebius-0.3.24.dist-info/licenses/AUTHORS
nebius-0.3.24.dist-info/licenses/LICENSE
nebius-0.3.24.dist-info/licenses/NOTICE.md
nebius-0.3.24.dist-info/METADATA
nebius-0.3.24.dist-info/WHEEL
nebius-0.3.24.dist-info/top_level.txt
nebius-0.3.24.dist-info/RECORD
