Metadata-Version: 2.4
Name: nebius
Version: 0.3.24
Summary: Nebius Python SDK
Author-email: Daniil Drizhuk <complynx@nebius.com>, Ivan Kornilov <ivan.kornilov@nebius.com>, Marat Reymers <marat-reymers@nebius.com>, Andrei Zenkov <andrei.zenkov@nebius.com>
License: The MIT License (MIT)
Requires-Python: >=3.10
License-File: LICENSE
License-File: NOTICE.md
License-File: AUTHORS
Requires-Dist: cryptography>=40.0.0
Requires-Dist: pyyaml>=5
Requires-Dist: grpcio>=1.56.2
Requires-Dist: PyJWT>=2.0.0
Requires-Dist: certifi>=2022.6.15
Requires-Dist: protobuf>=5.29.1
Requires-Dist: grpcio-status>=1.56.2
Requires-Dist: portalocker>=2.8.1
Requires-Dist: aiohttp>=3.8.5
Provides-Extra: windows
Requires-Dist: certifi-win32; extra == "windows"
Provides-Extra: dev
Requires-Dist: pytest>=8.0; extra == "dev"
Requires-Dist: pytest-asyncio>=0.24.0; extra == "dev"
Requires-Dist: pytest-subtests>=0.3.0; extra == "dev"
Requires-Dist: tox>=4.0; extra == "dev"
Requires-Dist: mypy>=1.13; extra == "dev"
Requires-Dist: black>=24.10; extra == "dev"
Requires-Dist: ruff>=0.7; extra == "dev"
Requires-Dist: grpc-stubs>=1.53; extra == "dev"
Requires-Dist: types-protobuf>=5.29.1; extra == "dev"
Requires-Dist: types-PyYAML>=5.0; extra == "dev"
Provides-Extra: generators
Requires-Dist: m2r2>=0.3; extra == "generators"
Requires-Dist: grpcio-tools>=1.56.2; extra == "generators"
Requires-Dist: mypy-protobuf>=3.6; extra == "generators"
Requires-Dist: protovalidate>=0.5; extra == "generators"
Requires-Dist: pydoctor<25.0,>=24.11.2; extra == "generators"
Requires-Dist: beautifulsoup4>=4.12.3; extra == "generators"
Requires-Dist: tomlkit>=0.13.2; extra == "generators"
Dynamic: license-file
